Workbook

Sheet Cover
C16: Company: Apple Inc
C17: Prepared By: Kieran O'Connell
C18: Purpose: Financial Modeling and Valuation Analysis

Sheet Assumptions
A1: Assumption | B1: Value
A2: Revenue Growth | B2: 0.055
A3: Gross Margin | B3: =AVERAGE(Historical!B11:D11) -> 0.44549037
A4: Operating Margin | B4: 0.315
A5: Operating Exepense | B5: 0.145
A6: Tax Rate | B6: 0.21
A7: CapEx % Revenue | B7: 0.035
A8: D&A % Revenue | B8: 0.025
A9: ΔNWC % Revenue | B9: 0.01
A10: Growth Rate | B10: 0.0275
A11: Terminal Growth | B11: ='Free Cash Flow'!F7*(1+B10)/(WACC!B13-B10) -> 2301247.8

Sheet WACC
A1: Input | B1: Value
A2: Risk Free Rate (Rf) | B2: 0.04
A3: Beta | B3: 1.2
A4: Market Return | B4: 0.085
A5: Cost of debtr | B5: 0.045
A6: Tax Rate | B6: =Assumptions!B6 -> 0.21
A8: Cost of Capital:
A9: Cost of Equity (utilizing CAPM) | B9: =B2+B3*(B4-B2) -> 0.094
A10: After Tax Cost of Debt | B10: =B5*(1-B6) -> 0.03555
A11: Weight of Equity | B11: 0.75
A12: Weight of debt | B12: 0.25
A13: WACC | B13: =B11*B9+B10*B12 -> 0.0793875

Sheet Historical
A1: ($ millions) | B1: 2022 | C1: 2023 | D1: 2024
A2: Revenue | B2: 394328 | C2: 383285 | D2: 391035
A3: COGS | B3: 223546 | C3: 214137 | D3: 210352
A4: Gross Profit | B4: =B2-B3 -> 170782 | C4: =C2-C3 -> 169148 | D4: =D2-D3 -> 180683
A5: Operating Expenses | B5: 51345 | C5: 54847 | D5: 57467
A6: Operating Income (EBIT) | B6: 119437 | C6: 114301 | D6: 123216
A7: Taxes | B7: 19300 | C7: 16741 | D7: 29749
A8: Net Income | B8: 99803 | C8: 96995 | D8: 93736
A10: Important Margins | B10: 2022 | C10: 2023 | D10: 2024
A11: Gross Margin | B11: =B4/B2 -> 0.43309631 | C11: =C4/C2 -> 0.4413113 | D11: =D4/D2 -> 0.4620635
A12: Operating Margin | B12: =B6/B2 -> 0.30288744 | C12: =C6/C2 -> 0.29821412 | D12: =D6/D2 -> 0.31510223
A13: Net Margin | B13: =B6/B2 -> 0.30288744 | C13: =C6/C2 -> 0.29821412 | D13: =D6/D2 -> 0.31510223
A15: Growth | B15: =C1 -> 2023 | C15: =D1 -> 2024
A16: Revenue Growth | B16: =(C2/B2)-1 -> -0.028004605 | C16: =(D2/C2)-1 -> 0.020219941
A17: Net Income Growth | B17: =(C6/B6)-1 -> -0.04300175 | C17: =(D6/C6)-1 -> 0.077995818

Sheet Income Statement(S)
A1: Year | B1: 2024 | C1: =1+B1 -> 2025 | D1: =1+C1 -> 2026 | E1: =1+D1 -> 2027 | F1: =1+E1 -> 2028 | G1: =1+F1 -> 2029
A2: Revenue | B2: =Historical!D2 -> 391035 | C2: =B2*(1+Assumptions!$B$2) -> 412541.92 | D2: =C2*(1+Assumptions!$B$2) -> 435231.73 | E2: =D2*(1+Assumptions!$B$2) -> 459169.48 | F2: =E2*(1+Assumptions!$B$2) -> 484423.8 | G2: =F2*(1+Assumptions!$B$2) -> 511067.11
A3: COGS | B3: =Historical!D3 -> 210352 | C3: =C2*(1-Assumptions!$B$3) -> 228758.47 | D3: =D2*(1-Assumptions!$B$3) -> 241340.19 | E3: =E2*(1-Assumptions!$B$3) -> 254613.9 | F3: =F2*(1-Assumptions!$B$3) -> 268617.66 | G3: =G2*(1-Assumptions!$B$3) -> 283391.63
A4: Gross Profit | B4: =B2-B3 -> 180683 | C4: =C2-C3 -> 183783.45 | D4: =D2-D3 -> 193891.54 | E4: =E2-E3 -> 204555.58 | F4: =F2-F3 -> 215806.13 | G4: =G2-G3 -> 227675.47
A5: Operating Expenses | B5: =Historical!D5 -> 57467 | C5: =C2*Assumptions!$B$5 -> 59818.579 | D5: =D2*Assumptions!$B$5 -> 63108.601 | E5: =E2*Assumptions!$B$5 -> 66579.574 | F5: =F2*Assumptions!$B$5 -> 70241.451 | G5: =G2*Assumptions!$B$5 -> 74104.73
A6: EBIT | B6: =Historical!D6 -> 123216 | C6: =C4-C5 -> 123964.87 | D6: =D4-D5 -> 130782.94 | E6: =E4-E5 -> 137976 | F6: =F4-F5 -> 145564.68 | G6: =G4-G5 -> 153570.74
A7: Taxes | B7: =B6*21% -> 25875.36 | C7: =C6*21% -> 26032.624 | D7: =D6*21% -> 27464.418 | E7: =E6*21% -> 28974.961 | F7: =F6*21% -> 30568.584 | G7: =G6*21% -> 32249.856
A8: Net Income | B8: =B6-B7 -> 97340.64 | C8: =C6-C7 -> 97932.251 | D8: =D6-D7 -> 103318.52 | E8: =E6-E7 -> 109001.04 | F8: =F6-F7 -> 114996.1 | G8: =G6-G7 -> 121320.89

Sheet Free Cash Flow
A1: Year | B1: 2025 | C1: 2026 | D1: 2027 | E1: 2028 | F1: 2029
A2: EBIT | B2: ='Income Statement(S)'!C6 -> 123964.87 | C2: ='Income Statement(S)'!D6 -> 130782.94 | D2: ='Income Statement(S)'!E6 -> 137976 | E2: ='Income Statement(S)'!F6 -> 145564.68 | F2: ='Income Statement(S)'!G6 -> 153570.74
A3: NOPAT | B3: =B2*(1-Assumptions!$B$6) -> 97932.251 | C3: =C2*(1-Assumptions!$B$6) -> 103318.52 | D3: =D2*(1-Assumptions!$B$6) -> 109001.04 | E3: =E2*(1-Assumptions!$B$6) -> 114996.1 | F3: =F2*(1-Assumptions!$B$6) -> 121320.89
A4: D&A | B4: ='Income Statement(S)'!B2*Assumptions!$B$8 -> 9775.875 | C4: ='Income Statement(S)'!C2*Assumptions!$B$8 -> 10313.548 | D4: ='Income Statement(S)'!D2*Assumptions!$B$8 -> 10880.793 | E4: ='Income Statement(S)'!E2*Assumptions!$B$8 -> 11479.237 | F4: ='Income Statement(S)'!F2*Assumptions!$B$8 -> 12110.595
A5: CapEx | B5: ='Income Statement(S)'!B2*Assumptions!$B$7 -> 13686.225 | C5: ='Income Statement(S)'!C2*Assumptions!$B$7 -> 14438.967 | D5: ='Income Statement(S)'!D2*Assumptions!$B$7 -> 15233.111 | E5: ='Income Statement(S)'!E2*Assumptions!$B$7 -> 16070.932 | F5: ='Income Statement(S)'!F2*Assumptions!$B$7 -> 16954.833
A6: DCF | B6: =('Income Statement(S)'!C2-'Income Statement(S)'!B2)*Assumptions!$B$9 -> 215.06925 | C6: =('Income Statement(S)'!D2-'Income Statement(S)'!C2)*Assumptions!$B$9 -> 226.89806 | D6: =('Income Statement(S)'!E2-'Income Statement(S)'!D2)*Assumptions!$B$9 -> 239.37745 | E6: =('Income Statement(S)'!F2-'Income Statement(S)'!E2)*Assumptions!$B$9 -> 252.54321 | F6: =('Income Statement(S)'!G2-'Income Statement(S)'!F2)*Assumptions!$B$9 -> 266.43309
A7: FCF | B7: =B3+B4-B5-B6 -> 93806.831 | C7: =C3+C4-C5-C6 -> 98966.207 | D7: =D3+D4-D5-D6 -> 104409.35 | E7: =E3+E4-E5-E6 -> 110151.86 | F7: =F3+F4-F5-F6 -> 116210.22

Sheet DCF Valuatiobn
A1: Year | B1: 2025 | C1: 2026 | D1: 2027 | E1: 2028 | F1: 2029
A2: FCF | B2: {='Free Cash Flow'!B7:F7} -> 93806.831 | C2: 98966.207 | D2: 104409.35 | E2: 110151.86 | F2: 116210.22
A3: Discount Factor | B3: =1/(1+WACC!$B$13)^1 -> 0.92645134 | C3: =1/(1+WACC!$B$13)^2 -> 0.85831209 | D3: =1/(1+WACC!$B$13)^3 -> 0.79518439 | E3: =1/(1+WACC!$B$13)^4 -> 0.73669965 | F3: =1/(1+WACC!$B$13)^5 -> 0.68251638
A4: Present Value of FCF | B4: =B2*B3 -> 86907.465 | C4: =C2*C3 -> 84943.892 | D4: =D2*D3 -> 83024.684 | E4: =E2*E3 -> 81148.839 | F4: =F2*F3 -> 79315.375
A6: Discount Terminal | B6: =Assumptions!B11/(1+WACC!B13)^5 -> 1570639.3
A7: Enterprise Value | B7: =SUM(B4:F4)+B6 -> 1985979.6
A8: Equity Value | B8: =B7-110000+140000 -> 2015979.6
A9: Share Price | B9: =B8/15500 -> 130.0632

Sheet Dashboard
A1: Apple Inc. DCF Valuation Model
A2: Prepared by Kieran O’Connell
A4: Metric | B4: Value
A5: Share Price | B5: ='DCF Valuatiobn'!B9 -> 130.0632
A6: Enterprise Value | B6: ='DCF Valuatiobn'!B7 -> 1985979.6
A7: Equity Value | B7: ='DCF Valuatiobn'!B8 -> 2015979.6
A8: WACC | B8: =WACC!B13 -> 0.0793875
A9: Terminal Growth | B9: =Assumptions!B11 -> 2301247.8
