Workbook
Name All_in_Rate: INPUTS!$B$13
Name Amoritization: INPUTS!$B$14
Name BaseRate: INPUTS!$B$11
Name Cash_Sweep: INPUTS!$B$15
Name Debt_EV: INPUTS!$B$9
Name Enterprise_Value: INPUTS!$B$4
Name Entry_EBITDA: INPUTS!$B$2
Name Entry_Multiple: INPUTS!$B$3
Name Exit_Multiple: INPUTS!$B$5
Name Holding_Period: INPUTS!$B$6
Name Min_Cash: INPUTS!$B$16
Name Spread_TLB: INPUTS!$B$12
Name Tax_Rate: INPUTS!$B$23

Sheet README
A1: Model Name: Private Equity LBO & Acquisition Model - Sample Deal Analysis
A2: Purpose: Evaluate acqiusition of TargetCo using leveraged buyout structure
C3: =TODAY() -> 46099
C4: By: Kieran O'Connell
A5: Key Features: | D5: Sign Convention
A6: Units: | B6: $ In Millions | D6: Outflows = Negative
A7: Time Period: | B7: Annual (Year 0 - Year 5) | D7: Inflows = Positiv
A9: Extra: | D9: Model Assumptions:
A10: Transaction structuring (Sources and Uses) | D10: Entry multiple based valuation
A11: Debt Modeling with sweep | D11: Exit via EBITDA multiple
A12: Pro forma financials | D12: Debt sweep applied to excess cash
A13: IRR/ MOIC analysis | D13: No Dividends (or optional toggle)
A14: Sensatiitiy analysis

Sheet TRANSACTION
A1: Enterprise Value: | B1: =Entry_Multiple * Entry_EBITDA -> 1000
A3: Net Debt:
A4: Debt Raised: | B4: =Enterprise_Value * Debt_EV -> 600
A5: Cash Acquiried: | B5: =0 -> 0
A6: Net Debt: | B6: =B4-B5 -> 600
A8: Equity Purchase Price | B8: =Enterprise_Value-B6 -> 400
A10: Fees:
A11: Transaction Fees (% of EV): | B11: 0.02
A12: Fees: | B12: =Enterprise_Value * B11 -> 20
A13: Equity Contribution: | B13: =B8+B12 -> 420

Sheet INPUTS
A1: Transaction Assumptions
A2: Entry EBITDA: | B2: 100
A3: Entry Multiple: | B3: 10
A4: Enterprise Value: | B4: =B2*B3 -> 1000
A5: Exit Multiple: | B5: 11
A6: Holding Period (Yrs) | B6: 5
A8: Financing Assumptions
A9: Debt % of EV | B9: 0.6
A10: Equity % | B10: =1-B9 -> 0.4
A11: Interest Rate (Base) | B11: 0.05
A12: Spread (TLB) | B12: 0.03
A13: All-in Rate | B13: =B11+B12 -> 0.08
A14: Amoritization % | B14: 0.05
A15: Cash Sweep | B15: 0.5
A16: Minimum Cash | B16: 10
A18: Operating Assumptions
A19: Revenue Growth | B19: 0.05
A20: EBITDA Margin | B20: 0.25
A21: CapEX % Revenue | B21: 0.03
A22: Change in NWC % Revenue | B22: 0.02
A23: Tax Rate | B23: 0.25
A25: Synergies
A26: Revenue Synergy Growth | B26: 0.02
A27: Cost Synergy (% Of EBITDA) | B27: 0.05
A28: Integration Costs (One Time) | B28: =10 -> 10

Sheet SOURCES_USES
A1: Uses:
A2: Equity Purchase Price | B2: 1000
A3: Transaction Fees | B3: =TRANSACTION!B12 -> 20
A4: Total Uses | B4: =SUM(B2:B3) -> 1020
A6: Sources:
A7: Debt Issued | B7: =Debt_EV*Enterprise_Value -> 600
A8: Equity Contribution | B8: =B4-B7 -> 420
A9: Total Sources | B9: =SUM(B7,B8) -> 1020
A11: Sources - Uses | B11: =B4-B9 -> 0

Sheet DEBT
E1: Year
B2: Debt Schedule: | C2: 0 | D2: 1 | E2: 2 | F2: 3 | G2: 4 | H2: 5
B3: Beg Debt | C3: 0 | D3: =C10 -> 600 | E3: =D10 -> 570 | F3: =E10 -> 540 | G3: =F10 -> 510 | H3: =G10 -> 480
B4: Debt Issued: | C4: =600 -> 600
B5: Interest Rate | C5: =8% -> 0.08 | D5: =8% -> 0.08 | E5: =8% -> 0.08 | F5: =8% -> 0.08 | G5: =8% -> 0.08 | H5: =8% -> 0.08
B6: Interest Expense | D6: =D3*D5 -> 48 | E6: =E3*E5 -> 45.6 | F6: =F3*F5 -> 43.2 | G6: =G3*G5 -> 40.8 | H6: =H3*H5 -> 38.4
B7: Amoritization | D7: =$C$4*Amoritization -> 30 | E7: =$C$4*Amoritization -> 30 | F7: =$C$4*Amoritization -> 30 | G7: =$C$4*Amoritization -> 30 | H7: =$C$4*Amoritization -> 30
B8: Cash Available | D8: =OPS!B11+FIN_STMNTS!B23-Min_Cash -> 25.6875 | E8: =OPS!C11-Min_Cash -> 20.571875 | F8: =OPS!D11-Min_Cash -> 25.610469 | G8: =OPS!E11-Min_Cash -> 30.810992 | H8: =OPS!F11-Min_Cash -> 36.181542
B9: Optional Sweep | D9: 0 | E9: 0 | F9: 0 | G9: 0 | H9: 0
B10: Ending Debt | C10: =C4-C7-C9 -> 600 | D10: =D3-D7-D9 -> 570 | E10: =E3-E7-E9 -> 540 | F10: =F3-F7-F9 -> 510 | G10: =G3-G7-G9 -> 480 | H10: =H3-H7-H9 -> 450

Sheet OPS
A1: OPS: | B1: Year 1: | C1: Year 2: | D1: Year 3 | E1: Year 4: | F1: Year 5:
A2: Revenue | B2: =Entry_EBITDA/INPUTS!$B$20 * (1+RETURNS!$B$2) -> 420 | C2: =B2*(1+RETURNS!$B$2) -> 441 | D2: =C2*(1+RETURNS!$B$2) -> 463.05 | E2: =D2*(1+RETURNS!$B$2) -> 486.2025 | F2: =E2*(1+RETURNS!$B$2) -> 510.51263
A3: EBITDA | B3: =B2*INPUTS!$B$20 -> 105 | C3: =C2*INPUTS!$B$20 -> 110.25 | D3: =D2*INPUTS!$B$20 -> 115.7625 | E3: =E2*INPUTS!$B$20 -> 121.55063 | F3: =F2*INPUTS!$B$20 -> 127.62816
A4: Synergy: | B4: =B3*INPUTS!$B$27 -> 5.25 | C4: =C3*INPUTS!$B$27 -> 5.5125 | D4: =D3*INPUTS!$B$27 -> 5.788125 | E4: =E3*INPUTS!$B$27 -> 6.0775313 | F4: =F3*INPUTS!$B$27 -> 6.3814078
A5: EBITDA w/ Synergy | B5: =SUM(B3:B4) -> 110.25 | C5: =SUM(C3:C4) -> 115.7625 | D5: =SUM(D3:D4) -> 121.55062 | E5: =SUM(E3:E4) -> 127.62816 | F5: =SUM(F3:F4) -> 134.00956
A6: Interest | B6: =DEBT!D3*DEBT!D5 -> 48 | C6: =DEBT!E3*DEBT!E5 -> 45.6 | D6: =DEBT!F3*DEBT!F5 -> 43.2 | E6: =DEBT!G3*DEBT!G5 -> 40.8 | F6: =DEBT!H3*DEBT!H5 -> 38.4
A7: EBT | B7: =B5-B6 -> 62.25 | C7: =C5-C6 -> 70.1625 | D7: =D5-D6 -> 78.350625 | E7: =E5-E6 -> 86.828156 | F7: =F5-F6 -> 95.609564
A8: Taxes | B8: =B7*Tax_Rate -> 15.5625 | C8: =C7*Tax_Rate -> 17.540625 | D8: =D7*Tax_Rate -> 19.587656 | E8: =E7*Tax_Rate -> 21.707039 | F8: =F7*Tax_Rate -> 23.902391
A9: CapEX | B9: =B2*INPUTS!$B$21 -> 12.6 | C9: =C2*INPUTS!$B$21 -> 13.23 | D9: =D2*INPUTS!$B$21 -> 13.8915 | E9: =E2*INPUTS!$B$21 -> 14.586075 | F9: =F2*INPUTS!$B$21 -> 15.315379
A10: Change in NWC | B10: =B2*INPUTS!$B$22 -> 8.4 | C10: =C2*INPUTS!$B$22 -> 8.82 | D10: =D2*INPUTS!$B$22 -> 9.261 | E10: =E2*INPUTS!$B$22 -> 9.72405 | F10: =F2*INPUTS!$B$22 -> 10.210253
A11: FCF | B11: =B5-B6-B8-B9-B10 -> 25.6875 | C11: =C5-C6-C8-C9-C10 -> 30.571875 | D11: =D5-D6-D8-D9-D10 -> 35.610469 | E11: =E5-E6-E8-E9-E10 -> 40.810992 | F11: =F5-F6-F8-F9-F10 -> 46.181542

Sheet FIN_STMNTS
C1: Simplified Income Statement
B2: Year 1: | C2: Year 2: | D2: Year 3 | E2: Year 4: | F2: Year 5:
A3: Revenue: | B3: {=OPS!B2:F2} -> 420 | C3: 441 | D3: 463.05 | E3: 486.2025 | F3: 510.51263
A4: EBITDA | B4: =OPS!B5 -> 110.25 | C4: =OPS!C5 -> 115.7625 | D4: =OPS!D5 -> 121.55062 | E4: =OPS!E5 -> 127.62816 | F4: =OPS!F5 -> 134.00956
A5: D&A | B5: =B3*2% -> 8.4 | C5: =C3*2% -> 8.82 | D5: =D3*2% -> 9.261 | E5: =E3*2% -> 9.72405 | F5: =F3*2% -> 10.210253
A6: EBIT | B6: =B4-B5 -> 101.85 | C6: =C4-C5 -> 106.9425 | D6: =D4-D5 -> 112.28963 | E6: =E4-E5 -> 117.90411 | F6: =F4-F5 -> 123.79931
A7: Interest | B7: {=DEBT!D6:H6} -> 48 | C7: 45.6 | D7: 43.2 | E7: 40.8 | F7: 38.4
A8: EBT | B8: =B6-B7 -> 53.85 | C8: =C6-C7 -> 61.3425 | D8: =D6-D7 -> 69.089625 | E8: =E6-E7 -> 77.104106 | F8: =F6-F7 -> 85.399312
A9: Taxes | B9: =B8*25% -> 13.4625 | C9: =C8*25% -> 15.335625 | D9: =D8*25% -> 17.272406 | E9: =E8*25% -> 19.276027 | F9: =F8*25% -> 21.349828
A10: Net Income | B10: =B8-B9 -> 40.3875 | C10: =C8-C9 -> 46.006875 | D10: =D8-D9 -> 51.817219 | E10: =E8-E9 -> 57.82808 | F10: =F8-F9 -> 64.049484
C12: Simplified Cash Flow Statement
B13: Year 1: | C13: Year 2: | D13: Year 3 | E13: Year 4: | F13: Year 5:
A14: EBI | B14: =B6*(1-25%) -> 76.3875 | C14: =C6*(1-25%) -> 80.206875 | D14: =D6*(1-25%) -> 84.217219 | E14: =E6*(1-25%) -> 88.42808 | F14: =F6*(1-25%) -> 92.849484
A15: D&A | B15: =B3*2% -> 8.4 | C15: =C3*2% -> 8.82 | D15: =D3*2% -> 9.261 | E15: =E3*2% -> 9.72405 | F15: =F3*2% -> 10.210253
A16: CapEx | B16: {=OPS!B9:F9} -> 12.6 | C16: 13.23 | D16: 13.8915 | E16: 14.586075 | F16: 15.315379
A17: Change In NWC | B17: {=OPS!B10:F10} -> 8.4 | C17: 8.82 | D17: 9.261 | E17: 9.72405 | F17: 10.210253
A18: FCF | B18: =B14+B15-B16-B17 -> 63.7875 | C18: =C14+C15-C16-C17 -> 66.976875 | D18: =D14+D15-D16-D17 -> 70.325719 | E18: =E14+E15-E16-E17 -> 73.842005 | F18: =F14+F15-F16-F17 -> 77.534105
A19: Debt Impact
A20: Amortization | B20: {=DEBT!D7:H7} -> 30 | C20: 30 | D20: 30 | E20: 30 | F20: 30
A21: Total Debt Impact | B21: =B20 -> 30 | C21: =C20 -> 30 | D21: =D20 -> 30 | E21: =E20 -> 30 | F21: =F20 -> 30
A22: Cash Change | B22: =B18-B21 -> 33.7875 | C22: =C18-C21 -> 36.976875 | D22: =D18-D21 -> 40.325719 | E22: =E18-E21 -> 43.842005 | F22: =F18-F21 -> 47.534105
A23: Beg Cash | B23: =INPUTS!B28 -> 10 | C23: =B24 -> 43.7875 | D23: =C24 -> 80.764375 | E23: =D24 -> 121.09009 | F23: =E24 -> 164.9321
A24: Ending Cash | B24: =B23+B22 -> 43.7875 | C24: =C23+C22 -> 80.764375 | D24: =D23+D22 -> 121.09009 | E24: =E23+E22 -> 164.9321 | F24: =F23+F22 -> 212.4662
C26: Simplifid Balance Sheet
B27: Year 1: | C27: Year 2: | D27: Year 3 | E27: Year 4: | F27: Year 5:
A28: Assets:
A29: Cash | B29: =B24 -> 43.7875 | C29: =C24 -> 80.764375 | D29: =D24 -> 121.09009 | E29: =E24 -> 164.9321 | F29: =F24 -> 212.4662
A30: Operating Assets: | B30: =B37-B29 -> 986.6 | C30: =C37-C29 -> 965.63 | D30: =D37-D29 -> 947.1215 | E30: =E37-E29 -> 931.10757 | F30: =F37-F29 -> 917.62295
A31: Total Assets | B31: =SUM(B29:B30) -> 1030.3875 | C31: =SUM(C29:C30) -> 1046.3944 | D31: =SUM(D29:D30) -> 1068.2116 | E31: =SUM(E29:E30) -> 1096.0397 | F31: =SUM(F29:F30) -> 1130.0892
A32: Liabilities:
A33: Debt | B33: =DEBT!D10 -> 570 | C33: =DEBT!E10 -> 540 | D33: =DEBT!F10 -> 510 | E33: =DEBT!G10 -> 480 | F33: =DEBT!H10 -> 450
A34: Equity
A35: Initial Equity | B35: =SOURCES_USES!$B$8 -> 420 | C35: =SOURCES_USES!$B$8 -> 420 | D35: =SOURCES_USES!$B$8 -> 420 | E35: =SOURCES_USES!$B$8 -> 420 | F35: =SOURCES_USES!$B$8 -> 420
A36: RE | B36: =B10 -> 40.3875 | C36: =C10+B36 -> 86.394375 | D36: =D10+C36 -> 138.21159 | E36: =E10+D36 -> 196.03967 | F36: =F10+E36 -> 260.08916
A37: Liabilites + SE | B37: =B33+B35+B36 -> 1030.3875 | C37: =C33+C35+C36 -> 1046.3944 | D37: =D33+D35+D36 -> 1068.2116 | E37: =E33+E35+E36 -> 1096.0397 | F37: =F33+F35+F36 -> 1130.0892

Sheet RETURNS
A1: Returns Analysis
A2: Revenue Growth (Driver) | B2: 0.05
A3: Exit Year: | B3: 5
A4: Exit EBITDA: | B4: =FIN_STMNTS!F4 -> 134.00956
A5: Exit Multiple: | B5: 11
A6: Exit Enterprise Value: | B6: =B4*B5 -> 1474.1052
A8: Less: Ending Debt: | B8: =DEBT!H10 -> 450
A9: Add: Cash: | B9: =FIN_STMNTS!F24 -> 212.4662
A10: Equity Value at Exit: | B10: =B6-B8+B9 -> 1236.5714
A12: Initial Equity Invested: | B12: =SOURCES_USES!B8 -> 420
A13: MOIC: | B13: =B10/B12 -> 2.9442176
A14: IRR: | B14: Year 0 | C14: Year 1 | D14: Year 2 | E14: Year 3 | F14: Year 4 | G14: Year 5
A15: Cash Flow | B15: -420 | C15: 0 | D15: 0 | E15: 0 | F15: 0 | G15: =B10 -> 1236.5714
A16: IRR: | B16: =IRR(B15:G15) -> 0.24106344
