Workbook
Name All_in_Rate: INPUTS!$B$13
Name Amoritization: INPUTS!$B$14
Name BaseRate: INPUTS!$B$11
Name Cash_Sweep: INPUTS!$B$15
Name Debt_EV: INPUTS!$B$9
Name Enterprise_Value: INPUTS!$B$4
Name Entry_EBITDA: INPUTS!$B$2
Name Entry_Multiple: INPUTS!$B$3
Name Exit_Multiple: INPUTS!$B$5
Name Holding_Period: INPUTS!$B$6
Name Min_Cash: INPUTS!$B$16
Name Spread_TLB: INPUTS!$B$12
Name Tax_Rate: INPUTS!$B$23

Sheet README
A1: Model Name: Private Equity LBO & Acquisition Model - Sample Deal Analysis
A2: Purpose: Evaluate acqiusition of TargetCo using leveraged buyout structure
C3: =TODAY() -> 46102
B4: By: Kieran O'Connell |Accounting and Finance Student

Sheet TRANSACTION
A1: Enterprise Value: | B1: =Entry_Multiple * Entry_EBITDA -> 1000
A3: Net Debt:
A4: Debt Raised: | B4: =Enterprise_Value * Debt_EV -> 600
A5: Cash Acquiried: | B5: =0 -> 0
A6: Net Debt: | B6: =B4-B5 -> 600
A8: Equity Purchase Price | B8: =Enterprise_Value-B6 -> 400
A10: Fees:
A11: Transaction Fees (% of EV): | B11: 0.02
A12: Fees: | B12: =Enterprise_Value * B11 -> 20
A13: Equity Contribution: | B13: =B8+B12 -> 420

Sheet INPUTS
A1: Transaction Assumptions | D1: Uses:
A2: Entry EBITDA: | B2: 100 | D2: Equity Purchase Price | E2: 400
A3: Entry Multiple: | B3: 10 | D3: Transaction Fees | E3: =TRANSACTION!B12 -> 20
A4: Enterprise Value: | B4: =B2*B3 -> 1000 | D4: Total Uses | E4: =SUM(E2:E3) -> 420
A5: Exit Multiple: | B5: 11
A6: Holding Period (Yrs) | B6: 5 | D6: Sources:
D7: Debt Issued | E7: =Debt_EV*Enterprise_Value -> 600
A8: Financing Assumptions | D8: Equity Contribution | E8: =E4-E7 -> -180
A9: Debt % of EV | B9: 0.6 | D9: Total Sources | E9: =SUM(E7,E8) -> 420
A10: Equity % | B10: =1-B9 -> 0.4
A11: Interest Rate (Base) | B11: 0.05 | D11: Sources - Uses | E11: =E4-E9 -> 0
A12: Spread (TLB) | B12: 0.03
A13: All-in Rate | B13: =B11+B12 -> 0.08
A14: Amoritization % | B14: 0.05
A15: Cash Sweep | B15: 0.5
A16: Minimum Cash | B16: 10
A18: Operating Assumptions
A19: Revenue Growth | B19: 0.05
A20: EBITDA Margin | B20: 0.25
A21: CapEX % Revenue | B21: 0.03
A22: Change in NWC % Revenue | B22: 0.02
A23: Tax Rate | B23: 0.25
A25: Synergies
A26: Revenue Synergy Growth | B26: 0.02
A27: Cost Synergy (% Of EBITDA) | B27: 0.05
A28: Integration Costs (One Time) | B28: =10 -> 10

Sheet DEBT
E1: Year
B2: Debt Schedule: | C2: 0 | D2: 1 | E2: 2 | F2: 3 | G2: 4 | H2: 5
B3: Beg Debt | C3: 0 | D3: =C10 -> 600 | E3: =D10 -> 554.3125 | F3: =E10 -> 512.79938 | G3: =F10 -> 465.55687 | H3: =G10 -> 412.07929
B4: Debt Issued: | C4: =600 -> 600
B5: Interest Rate | C5: =8% -> 0.08 | D5: =8% -> 0.08 | E5: =8% -> 0.08 | F5: =8% -> 0.08 | G5: =8% -> 0.08 | H5: =8% -> 0.08
B6: Interest Expense | D6: =D3*D5 -> 48 | E6: =E3*E5 -> 44.345 | F6: =F3*F5 -> 41.02395 | G6: =G3*G5 -> 37.24455 | H6: =H3*H5 -> 32.966343
B7: Amoritization | D7: =$C$4*Amoritization -> 30 | E7: =$C$4*Amoritization -> 30 | F7: =$C$4*Amoritization -> 30 | G7: =$C$4*Amoritization -> 30 | H7: =$C$4*Amoritization -> 30
B8: Cash Available | D8: =OPS!B11+FIN_STMNTS!B23-Min_Cash -> 25.6875 | E8: =OPS!C11-Min_Cash -> 21.513125 | F8: =OPS!D11-Min_Cash -> 27.242506 | G8: =OPS!E11-Min_Cash -> 33.47758 | H8: =OPS!F11-Min_Cash -> 40.256784
B9: Optional Sweep | D9: =MAX(0,D8-10) -> 15.6875 | E9: =MAX(0,E8-10) -> 11.513125 | F9: =MAX(0,F8-10) -> 17.242506 | G9: =MAX(0,G8-10) -> 23.47758 | H9: =MAX(0,H8-10) -> 30.256784
B10: Ending Debt | C10: =C4-C7-C9 -> 600 | D10: =D3-D7-D9 -> 554.3125 | E10: =E3-E7-E9 -> 512.79938 | F10: =F3-F7-F9 -> 465.55687 | G10: =G3-G7-G9 -> 412.07929 | H10: =H3-H7-H9 -> 351.8225

Sheet OPS
A1: OPS: | B1: Year 1: | C1: Year 2: | D1: Year 3 | E1: Year 4: | F1: Year 5:
A2: Revenue | B2: =Entry_EBITDA/INPUTS!$B$20 * (1+RETURNS!$B$2) -> 420 | C2: =B2*(1+RETURNS!$B$2) -> 441 | D2: =C2*(1+RETURNS!$B$2) -> 463.05 | E2: =D2*(1+RETURNS!$B$2) -> 486.2025 | F2: =E2*(1+RETURNS!$B$2) -> 510.51263
A3: EBITDA | B3: =B2*INPUTS!$B$20 -> 105 | C3: =C2*INPUTS!$B$20 -> 110.25 | D3: =D2*INPUTS!$B$20 -> 115.7625 | E3: =E2*INPUTS!$B$20 -> 121.55063 | F3: =F2*INPUTS!$B$20 -> 127.62816
A4: Synergy: | B4: =B3*INPUTS!$B$27 -> 5.25 | C4: =C3*INPUTS!$B$27 -> 5.5125 | D4: =D3*INPUTS!$B$27 -> 5.788125 | E4: =E3*INPUTS!$B$27 -> 6.0775313 | F4: =F3*INPUTS!$B$27 -> 6.3814078
A5: EBITDA w/ Synergy | B5: =SUM(B3:B4) -> 110.25 | C5: =SUM(C3:C4) -> 115.7625 | D5: =SUM(D3:D4) -> 121.55062 | E5: =SUM(E3:E4) -> 127.62816 | F5: =SUM(F3:F4) -> 134.00956
A6: Interest | B6: =DEBT!D3*DEBT!D5 -> 48 | C6: =DEBT!E3*DEBT!E5 -> 44.345 | D6: =DEBT!F3*DEBT!F5 -> 41.02395 | E6: =DEBT!G3*DEBT!G5 -> 37.24455 | F6: =DEBT!H3*DEBT!H5 -> 32.966343
A7: EBT | B7: =B5-B6 -> 62.25 | C7: =C5-C6 -> 71.4175 | D7: =D5-D6 -> 80.526675 | E7: =E5-E6 -> 90.383607 | F7: =F5-F6 -> 101.04322
A8: Taxes | B8: =B7*Tax_Rate -> 15.5625 | C8: =C7*Tax_Rate -> 17.854375 | D8: =D7*Tax_Rate -> 20.131669 | E8: =E7*Tax_Rate -> 22.595902 | F8: =F7*Tax_Rate -> 25.260805
A9: CapEX | B9: =B2*INPUTS!$B$21 -> 12.6 | C9: =C2*INPUTS!$B$21 -> 13.23 | D9: =D2*INPUTS!$B$21 -> 13.8915 | E9: =E2*INPUTS!$B$21 -> 14.586075 | F9: =F2*INPUTS!$B$21 -> 15.315379
A10: Change in NWC | B10: =B2*INPUTS!$B$22 -> 8.4 | C10: =C2*INPUTS!$B$22 -> 8.82 | D10: =D2*INPUTS!$B$22 -> 9.261 | E10: =E2*INPUTS!$B$22 -> 9.72405 | F10: =F2*INPUTS!$B$22 -> 10.210253
A11: Unlevered Cash flow | B11: =B5-B6-B8-B9-B10 -> 25.6875 | C11: =C5-C6-C8-C9-C10 -> 31.513125 | D11: =D5-D6-D8-D9-D10 -> 37.242506 | E11: =E5-E6-E8-E9-E10 -> 43.47758 | F11: =F5-F6-F8-F9-F10 -> 50.256784

Sheet FIN_STMNTS
C1: Simplified Income Statement
B2: Year 1: | C2: Year 2: | D2: Year 3 | E2: Year 4: | F2: Year 5:
A3: Revenue: | B3: {=OPS!B2:F2} -> 420 | C3: 441 | D3: 463.05 | E3: 486.2025 | F3: 510.51263
A4: EBITDA | B4: =OPS!B5 -> 110.25 | C4: =OPS!C5 -> 115.7625 | D4: =OPS!D5 -> 121.55062 | E4: =OPS!E5 -> 127.62816 | F4: =OPS!F5 -> 134.00956
A5: D&A | B5: =B3*2% -> 8.4 | C5: =C3*2% -> 8.82 | D5: =D3*2% -> 9.261 | E5: =E3*2% -> 9.72405 | F5: =F3*2% -> 10.210253
A6: EBIT | B6: =B4-B5 -> 101.85 | C6: =C4-C5 -> 106.9425 | D6: =D4-D5 -> 112.28963 | E6: =E4-E5 -> 117.90411 | F6: =F4-F5 -> 123.79931
A7: Interest | B7: {=DEBT!D6:H6} -> 48 | C7: 44.345 | D7: 41.02395 | E7: 37.24455 | F7: 32.966343
A8: EBT | B8: =B6-B7 -> 53.85 | C8: =C6-C7 -> 62.5975 | D8: =D6-D7 -> 71.265675 | E8: =E6-E7 -> 80.659557 | F8: =F6-F7 -> 90.832968
A9: Taxes | B9: =B8*25% -> 13.4625 | C9: =C8*25% -> 15.649375 | D9: =D8*25% -> 17.816419 | E9: =E8*25% -> 20.164889 | F9: =F8*25% -> 22.708242
A10: Net Income | B10: =B8-B9 -> 40.3875 | C10: =C8-C9 -> 46.948125 | D10: =D8-D9 -> 53.449256 | E10: =E8-E9 -> 60.494668 | F10: =F8-F9 -> 68.124726
C12: Simplified Cash Flow Statement
B13: Year 1: | C13: Year 2: | D13: Year 3 | E13: Year 4: | F13: Year 5:
A14: EBI | B14: =B6*(1-25%) -> 76.3875 | C14: =C6*(1-25%) -> 80.206875 | D14: =D6*(1-25%) -> 84.217219 | E14: =E6*(1-25%) -> 88.42808 | F14: =F6*(1-25%) -> 92.849484
A15: D&A | B15: =B3*2% -> 8.4 | C15: =C3*2% -> 8.82 | D15: =D3*2% -> 9.261 | E15: =E3*2% -> 9.72405 | F15: =F3*2% -> 10.210253
A16: CapEx | B16: {=OPS!B9:F9} -> 12.6 | C16: 13.23 | D16: 13.8915 | E16: 14.586075 | F16: 15.315379
A17: Change In NWC | B17: {=OPS!B10:F10} -> 8.4 | C17: 8.82 | D17: 9.261 | E17: 9.72405 | F17: 10.210253
A18: FCF | B18: =B14+B15-B16-B17 -> 63.7875 | C18: =C14+C15-C16-C17 -> 66.976875 | D18: =D14+D15-D16-D17 -> 70.325719 | E18: =E14+E15-E16-E17 -> 73.842005 | F18: =F14+F15-F16-F17 -> 77.534105
A19: Debt Impact
A20: Amortization | B20: {=DEBT!D7:H7} -> 30 | C20: 30 | D20: 30 | E20: 30 | F20: 30
A21: Total Debt Impact | B21: =B20 -> 30 | C21: =C20 -> 30 | D21: =D20 -> 30 | E21: =E20 -> 30 | F21: =F20 -> 30
A22: Cash Change | B22: =B18-B21 -> 33.7875 | C22: =C18-C21 -> 36.976875 | D22: =D18-D21 -> 40.325719 | E22: =E18-E21 -> 43.842005 | F22: =F18-F21 -> 47.534105
A23: Beg Cash | B23: =INPUTS!B28 -> 10 | C23: =B24 -> 43.7875 | D23: =C24 -> 80.764375 | E23: =D24 -> 121.09009 | F23: =E24 -> 164.9321
A24: Ending Cash | B24: =B23+B22 -> 43.7875 | C24: =C23+C22 -> 80.764375 | D24: =D23+D22 -> 121.09009 | E24: =E23+E22 -> 164.9321 | F24: =F23+F22 -> 212.4662
C26: Simplifid Balance Sheet
B27: Year 1: | C27: Year 2: | D27: Year 3 | E27: Year 4: | F27: Year 5:
A28: Assets:
A29: Cash | B29: =B24 -> 43.7875 | C29: =C24 -> 80.764375 | D29: =D24 -> 121.09009 | E29: =E24 -> 164.9321 | F29: =F24 -> 212.4662
A30: Operating Assets: | B30: =B37-B29 -> 370.9125 | C30: =C37-C29 -> 339.37063 | D30: =D37-D29 -> 305.25166 | E30: =E37-E29 -> 268.42674 | F30: =F37-F29 -> 228.76058
A31: Total Assets | B31: =SUM(B29:B30) -> 414.7 | C31: =SUM(C29:C30) -> 420.135 | D31: =SUM(D29:D30) -> 426.34175 | E31: =SUM(E29:E30) -> 433.35884 | F31: =SUM(F29:F30) -> 441.22678
A32: Liabilities:
A33: Debt | B33: =DEBT!D10 -> 554.3125 | C33: =DEBT!E10 -> 512.79938 | D33: =DEBT!F10 -> 465.55687 | E33: =DEBT!G10 -> 412.07929 | F33: =DEBT!H10 -> 351.8225
A34: Equity
A35: Initial Equity | B35: =INPUTS!$E$8 -> -180 | C35: =INPUTS!$E$8 -> -180 | D35: =INPUTS!$E$8 -> -180 | E35: =INPUTS!$E$8 -> -180 | F35: =INPUTS!$E$8 -> -180
A36: RE | B36: =B10 -> 40.3875 | C36: =C10+B36 -> 87.335625 | D36: =D10+C36 -> 140.78488 | E36: =E10+D36 -> 201.27955 | F36: =F10+E36 -> 269.40428
A37: Liabilites + SE | B37: =B33+B35+B36 -> 414.7 | C37: =C33+C35+C36 -> 420.135 | D37: =D33+D35+D36 -> 426.34175 | E37: =E33+E35+E36 -> 433.35884 | F37: =F33+F35+F36 -> 441.22678

Sheet RETURNS
A1: Returns Analysis
A2: Revenue Growth (Driver) | B2: 0.05
A3: Exit Year: | B3: 5
A4: Exit EBITDA: | B4: =FIN_STMNTS!F4 -> 134.00956
A5: Exit Multiple: | B5: 11
A6: Exit Enterprise Value: | B6: =B4*B5 -> 1474.1052
A8: Less: Ending Debt: | B8: =DEBT!H10 -> 351.8225
A9: Add: Cash: | B9: =FIN_STMNTS!F24 -> 212.4662
A10: Equity Value at Exit: | B10: =B6-B8+B9 -> 1334.7489
A12: Initial Equity Invested: | B12: =INPUTS!E8 -> -180
A13: MOIC: | B13: =B10/B12 -> -7.4152717
A14: IRR: | B14: Year 0 | C14: Year 1 | D14: Year 2 | E14: Year 3 | F14: Year 4 | G14: Year 5
A15: Cash Flow | B15: -420 | C15: 0 | D15: 0 | E15: 0 | F15: 0 | G15: =B10 -> 1334.7489
A16: IRR: | B16: =IRR(B15:G15) -> 0.26017267
A18: Value Creation Bridge
A19: Entry Enterprise value | B19: 1000
A20: EBITDA Growth | B20: 340
A21: Multiple expansion | B21: 134
A22: Exit Enterprise | B22: =SUM(B19:B21) -> 1474
A24: Equity Value Creation
A25: Net Debt | B25: 352
A26: Cash | B26: 212
A27: Equity Value | B27: =B22-B25+B26 -> 1334
A28: Initial Equity | B28: 420
A29: Gain | B29: =B27-B28 -> 914
